tests/__init__.py
tests/test_cli.py
tests/test_git2blog.py
git2blog-1.0.8.dist-info/LICENSE
git2blog-1.0.8.dist-info/METADATA
git2blog-1.0.8.dist-info/WHEEL
git2blog-1.0.8.dist-info/entry_points.txt
git2blog-1.0.8.dist-info/top_level.txt
git2blog-1.0.8.dist-info/RECORD
